fetchAZA/_version.py
fetchAZA/plotters.py
fetchAZA/readers.py
fetchAZA/timetools.py
fetchAZA/tools.py
fetchAZA/utilities.py
fetchAZA/writers.py
fetchaza-0.1.dev6.dist-info/licenses/LICENSE
fetchaza-0.1.dev6.dist-info/METADATA
fetchaza-0.1.dev6.dist-info/WHEEL
fetchaza-0.1.dev6.dist-info/top_level.txt
fetchaza-0.1.dev6.dist-info/RECORD
