Metadata-Version: 2.4
Name: fetchAZA
Version: 0.1.dev6
Summary: Repository to load data from Sonardyne Fetch AZA
Maintainer-email: Eleanor Frajka-Williams <eleanorfrajka@gmail.com>
License: MIT License
Project-URL: documentation, https://github.com/eleanorfrajka/fetchAZA
Project-URL: homepage, https://github.com/eleanorfrajka/fetchAZA
Project-URL: repository, https://github.com/eleanorfrajka/fetchAZA
Classifier: Programming Language :: Python :: 3 :: Only
Classifier: Programming Language :: Python :: 3.8
Classifier: Programming Language :: Python :: 3.9
Classifier: Programming Language :: Python :: 3.10
Classifier: Programming Language :: Python :: 3.11
Classifier: Programming Language :: Python :: 3.12
Requires-Python: >=3.8
License-File: LICENSE
Requires-Dist: netcdf4
Requires-Dist: xarray
Requires-Dist: numpy
Requires-Dist: matplotlib
Requires-Dist: scipy
Dynamic: license-file
